machofile/CLAUDE.md
machofile/FORMATTED_API_SUMMARY.md
machofile/LICENSE
machofile/PYPI_RELEASE_GUIDE.md
machofile/README.md
machofile/__init__.py
machofile/compare_imports.py
machofile/machofile.py
machofile/doc/API_documentation_machofile.md
machofile-2025.8.5.dist-info/licenses/LICENSE
machofile-2025.8.5.dist-info/METADATA
machofile-2025.8.5.dist-info/WHEEL
machofile-2025.8.5.dist-info/entry_points.txt
machofile-2025.8.5.dist-info/top_level.txt
machofile-2025.8.5.dist-info/RECORD
