Metadata-Version: 2.4
Name: machofile
Version: 2025.8.5
Summary: A Python module to parse Mach-O binary files
Author-email: Pasquale Stirparo <pstirparo@threatresearch.ch>
Maintainer-email: Pasquale Stirparo <pstirparo@threatresearch.ch>
License-Expression: MIT
Project-URL: Homepage, https://github.com/pasquales/machofile
Project-URL: Repository, https://github.com/pasquales/machofile
Project-URL: Documentation, https://github.com/pasquales/machofile/blob/main/API_documentation_machofile.md
Project-URL: Bug Tracker, https://github.com/pasquales/machofile/issues
Keywords: mach-o,macho,universal-binary,binary-parser,macos,ios,reverse-engineering,malware-analysis,security,python
Classifier: Development Status :: 5 - Production/Stable
Classifier: Intended Audience :: Developers
Classifier: Intended Audience :: Information Technology
Classifier: Intended Audience :: Science/Research
Classifier: Operating System :: OS Independent
Classifier: Programming Language :: Python :: 3
Classifier: Programming Language :: Python :: 3.7
Classifier: Programming Language :: Python :: 3.8
Classifier: Programming Language :: Python :: 3.9
Classifier: Programming Language :: Python :: 3.10
Classifier: Programming Language :: Python :: 3.11
Classifier: Programming Language :: Python :: 3.12
Classifier: Topic :: Security
Classifier: Topic :: Software Development :: Libraries :: Python Modules
Classifier: Topic :: System :: Operating System
Classifier: Topic :: Utilities
Requires-Python: >=3.7
License-File: LICENSE
Dynamic: license-file
